zenbu.py
zenbu-1.0.6.dist-info/LICENSE
zenbu-1.0.6.dist-info/METADATA
zenbu-1.0.6.dist-info/WHEEL
zenbu-1.0.6.dist-info/entry_points.txt
zenbu-1.0.6.dist-info/top_level.txt
zenbu-1.0.6.dist-info/RECORD
