Metadata-Version: 2.1
Name: zenbu
Version: 1.0.6
Summary: Jinja2 + YAML based config templater.
Home-page: https://github.com/metakirby5/zenbu
Author: Ethan Chan
Author-email: metakirby5@gmail.com
License: MIT
Keywords: zenbu config templater jinja2 yaml
Platform: UNKNOWN
Classifier: Development Status :: 5 - Production/Stable
Classifier: Environment :: Console
Classifier: Intended Audience :: End Users/Desktop
Classifier: Topic :: Utilities
Classifier: License :: OSI Approved :: MIT License
Classifier: Natural Language :: English
Classifier: Operating System :: POSIX :: Linux
Classifier: Programming Language :: Python :: 2
Classifier: Programming Language :: Python :: 3
Requires-Dist: argcomplete
Requires-Dist: colorlog
Requires-Dist: Jinja2
Requires-Dist: PyYAML
Requires-Dist: termcolor
Requires-Dist: watchdog
